quixpose/__init__.py
quixpose/__main__.py
quixpose/client.py
quixpose/tunnel.py
quixpose-0.1.1.dist-info/METADATA
quixpose-0.1.1.dist-info/WHEEL
quixpose-0.1.1.dist-info/licenses/LICENSE
quixpose-0.1.1.dist-info/RECORD
